vcommand/__init__.py
vcommand-0.0.2.dist-info/LICENSE
vcommand-0.0.2.dist-info/METADATA
vcommand-0.0.2.dist-info/WHEEL
vcommand-0.0.2.dist-info/top_level.txt
vcommand-0.0.2.dist-info/RECORD
